texttoaudio/__init__.py
texttoaudio/texttoaudio.py
textaudioconverter15-0.1.dist-info/METADATA
textaudioconverter15-0.1.dist-info/WHEEL
textaudioconverter15-0.1.dist-info/top_level.txt
textaudioconverter15-0.1.dist-info/RECORD
